fasttsfeatures/__init__.py
fasttsfeatures/_nbdev.py
fasttsfeatures/core.py
fasttsfeatures-0.0.10.dist-info/LICENSE
fasttsfeatures-0.0.10.dist-info/METADATA
fasttsfeatures-0.0.10.dist-info/WHEEL
fasttsfeatures-0.0.10.dist-info/entry_points.txt
fasttsfeatures-0.0.10.dist-info/top_level.txt
fasttsfeatures-0.0.10.dist-info/RECORD
