Metadata-Version: 2.1
Name: fasttsfeatures
Version: 0.0.10
Summary: Scalable time series features computation
Home-page: https://github.com/Nixtla/fasttsfeatures/tree/master/
Author: Nixtla and contributors
Author-email: fede.garza.ramirez@gmail.com
License: MIT License
Keywords: time series,features,static features,temporal features
Platform: UNKNOWN
Classifier: Development Status :: 3 - Alpha
Classifier: Intended Audience :: Developers
Classifier: Natural Language :: English
Classifier: Programming Language :: Python :: 3.7
Classifier: Programming Language :: Python :: 3.8
Classifier: License :: OSI Approved :: MIT License
Requires-Python: >=3.7
License-File: LICENSE
Requires-Dist: pip
Requires-Dist: packaging
Requires-Dist: pandas
Requires-Dist: pyarrow
Requires-Dist: python-dotenv
Requires-Dist: requests
Requires-Dist: s3fs
Requires-Dist: boto3
Provides-Extra: dev
